oalg/__init__.py
oalg-0.1.1.dist-info/METADATA
oalg-0.1.1.dist-info/WHEEL
oalg-0.1.1.dist-info/licenses/LICENSE.txt
oalg-0.1.1.dist-info/RECORD
