Metadata-Version: 2.1
Name: oalg
Version: 0.1.1
Summary: Collection of on-line algorithms.
Project-URL: Source, https://github.com/proggy/oalg
Project-URL: Homepage, https://github.com/proggy/oalg
Project-URL: Bug Tracker, https://github.com/proggy/oalg/issues
Author-email: Daniel Jung <proggy-contact@mailbox.org>
Maintainer-email: Daniel Jung <proggy-contact@mailbox.org>
License-File: LICENSE.txt
Classifier: License :: OSI Approved :: GNU General Public License v2 (GPLv2)
Classifier: Operating System :: OS Independent
Classifier: Programming Language :: Python :: 3
Requires-Python: >=2.5
